{
  "data_asset_type": null,
  "expectation_suite_name": "data_assistant_expectations",
  "expectations": [
    {
      "expectation_type": "expect_table_row_count_to_be_between",
      "kwargs": {
        "max_value": 3,
        "min_value": 3
      },
      "meta": {
        "profiler_details": {
          "metric_configuration": {
            "domain_kwargs": {},
            "metric_dependencies": null,
            "metric_name": "table.row_count",
            "metric_value_kwargs": null
          },
          "num_batches": 1
        }
      }
    },
    {
      "expectation_type": "expect_table_columns_to_match_set",
      "kwargs": {
        "column_set": [
          "b",
          "a",
          "e"
        ],
        "exact_match": null
      },
      "meta": {
        "profiler_details": {
          "success_ratio": 1.0
        }
      }
    },
    {
      "expectation_type": "expect_column_values_to_be_unique",
      "kwargs": {
        "column": "a"
      },
      "meta": {
        "profiler_details": {
          "metric_configuration": {
            "domain_kwargs": {
              "column": "a"
            },
            "metric_dependencies": null,
            "metric_name": "column_values.unique.unexpected_count",
            "metric_value_kwargs": null
          },
          "num_batches": 1
        }
      }
    },
    {
      "expectation_type": "expect_column_values_to_be_unique",
      "kwargs": {
        "column": "e"
      },
      "meta": {
        "profiler_details": {
          "metric_configuration": {
            "domain_kwargs": {
              "column": "e"
            },
            "metric_dependencies": null,
            "metric_name": "column_values.unique.unexpected_count",
            "metric_value_kwargs": null
          },
          "num_batches": 1
        }
      }
    },
    {
      "expectation_type": "expect_column_values_to_be_unique",
      "kwargs": {
        "column": "b"
      },
      "meta": {
        "profiler_details": {
          "metric_configuration": {
            "domain_kwargs": {
              "column": "b"
            },
            "metric_dependencies": null,
            "metric_name": "column_values.unique.unexpected_count",
            "metric_value_kwargs": null
          },
          "num_batches": 1
        }
      }
    },
    {
      "expectation_type": "expect_column_values_to_not_be_null",
      "kwargs": {
        "column": "a"
      },
      "meta": {
        "profiler_details": {
          "metric_configuration": {
            "domain_kwargs": {
              "column": "a"
            },
            "metric_dependencies": null,
            "metric_name": "column_values.nonnull.unexpected_count",
            "metric_value_kwargs": null
          },
          "num_batches": 1
        }
      }
    },
    {
      "expectation_type": "expect_column_values_to_not_be_null",
      "kwargs": {
        "column": "e"
      },
      "meta": {
        "profiler_details": {
          "metric_configuration": {
            "domain_kwargs": {
              "column": "e"
            },
            "metric_dependencies": null,
            "metric_name": "column_values.nonnull.unexpected_count",
            "metric_value_kwargs": null
          },
          "num_batches": 1
        }
      }
    },
    {
      "expectation_type": "expect_column_values_to_not_be_null",
      "kwargs": {
        "column": "b"
      },
      "meta": {
        "profiler_details": {
          "metric_configuration": {
            "domain_kwargs": {
              "column": "b"
            },
            "metric_dependencies": null,
            "metric_name": "column_values.nonnull.unexpected_count",
            "metric_value_kwargs": null
          },
          "num_batches": 1
        }
      }
    },
    {
      "expectation_type": "expect_column_min_to_be_between",
      "kwargs": {
        "column": "a",
        "max_value": 1,
        "min_value": 1,
        "strict_max": false,
        "strict_min": false
      },
      "meta": {
        "profiler_details": {
          "metric_configuration": {
            "domain_kwargs": {
              "column": "a"
            },
            "metric_dependencies": null,
            "metric_name": "column.min",
            "metric_value_kwargs": null
          },
          "num_batches": 1
        }
      }
    },
    {
      "expectation_type": "expect_column_max_to_be_between",
      "kwargs": {
        "column": "a",
        "max_value": 7,
        "min_value": 7,
        "strict_max": false,
        "strict_min": false
      },
      "meta": {
        "profiler_details": {
          "metric_configuration": {
            "domain_kwargs": {
              "column": "a"
            },
            "metric_dependencies": null,
            "metric_name": "column.max",
            "metric_value_kwargs": null
          },
          "num_batches": 1
        }
      }
    },
    {
      "expectation_type": "expect_column_values_to_be_between",
      "kwargs": {
        "column": "a",
        "max_value": 7,
        "min_value": 1,
        "mostly": 1.0,
        "strict_max": false,
        "strict_min": false
      },
      "meta": {
        "profiler_details": {
          "column_max_values_range_estimator": {
            "metric_configuration": {
              "domain_kwargs": {
                "column": "a"
              },
              "metric_dependencies": null,
              "metric_name": "column.max",
              "metric_value_kwargs": null
            },
            "num_batches": 1
          },
          "column_min_values_range_estimator": {
            "metric_configuration": {
              "domain_kwargs": {
                "column": "a"
              },
              "metric_dependencies": null,
              "metric_name": "column.min",
              "metric_value_kwargs": null
            },
            "num_batches": 1
          }
        }
      }
    },
    {
      "expectation_type": "expect_column_quantile_values_to_be_between",
      "kwargs": {
        "allow_relative_error": false,
        "column": "a",
        "quantile_ranges": {
          "quantiles": [
            0.25,
            0.5,
            0.75
          ],
          "value_ranges": [
            [
              1,
              1
            ],
            [
              4,
              4
            ],
            [
              7,
              7
            ]
          ]
        }
      },
      "meta": {
        "profiler_details": {
          "metric_configuration": {
            "domain_kwargs": {
              "column": "a"
            },
            "metric_dependencies": null,
            "metric_name": "column.quantile_values",
            "metric_value_kwargs": {
              "allow_relative_error": false,
              "quantiles": [
                0.25,
                0.5,
                0.75
              ]
            }
          },
          "num_batches": 1
        }
      }
    },
    {
      "expectation_type": "expect_column_median_to_be_between",
      "kwargs": {
        "column": "a",
        "max_value": 4.0,
        "min_value": 4.0,
        "strict_max": false,
        "strict_min": false
      },
      "meta": {
        "profiler_details": {
          "metric_configuration": {
            "domain_kwargs": {
              "column": "a"
            },
            "metric_dependencies": null,
            "metric_name": "column.median",
            "metric_value_kwargs": null
          },
          "num_batches": 1
        }
      }
    },
    {
      "expectation_type": "expect_column_mean_to_be_between",
      "kwargs": {
        "column": "a",
        "max_value": 4.0,
        "min_value": 4.0,
        "strict_max": false,
        "strict_min": false
      },
      "meta": {
        "profiler_details": {
          "metric_configuration": {
            "domain_kwargs": {
              "column": "a"
            },
            "metric_dependencies": null,
            "metric_name": "column.mean",
            "metric_value_kwargs": null
          },
          "num_batches": 1
        }
      }
    },
    {
      "expectation_type": "expect_column_stdev_to_be_between",
      "kwargs": {
        "column": "a",
        "max_value": 3.0,
        "min_value": 3.0,
        "strict_max": false,
        "strict_min": false
      },
      "meta": {
        "profiler_details": {
          "metric_configuration": {
            "domain_kwargs": {
              "column": "a"
            },
            "metric_dependencies": null,
            "metric_name": "column.standard_deviation",
            "metric_value_kwargs": null
          },
          "num_batches": 1
        }
      }
    },
    {
      "expectation_type": "expect_column_min_to_be_between",
      "kwargs": {
        "column": "e",
        "max_value": 2,
        "min_value": 2,
        "strict_max": false,
        "strict_min": false
      },
      "meta": {
        "profiler_details": {
          "metric_configuration": {
            "domain_kwargs": {
              "column": "e"
            },
            "metric_dependencies": null,
            "metric_name": "column.min",
            "metric_value_kwargs": null
          },
          "num_batches": 1
        }
      }
    },
    {
      "expectation_type": "expect_column_max_to_be_between",
      "kwargs": {
        "column": "e",
        "max_value": 8,
        "min_value": 8,
        "strict_max": false,
        "strict_min": false
      },
      "meta": {
        "profiler_details": {
          "metric_configuration": {
            "domain_kwargs": {
              "column": "e"
            },
            "metric_dependencies": null,
            "metric_name": "column.max",
            "metric_value_kwargs": null
          },
          "num_batches": 1
        }
      }
    },
    {
      "expectation_type": "expect_column_values_to_be_between",
      "kwargs": {
        "column": "e",
        "max_value": 8,
        "min_value": 2,
        "mostly": 1.0,
        "strict_max": false,
        "strict_min": false
      },
      "meta": {
        "profiler_details": {
          "column_max_values_range_estimator": {
            "metric_configuration": {
              "domain_kwargs": {
                "column": "e"
              },
              "metric_dependencies": null,
              "metric_name": "column.max",
              "metric_value_kwargs": null
            },
            "num_batches": 1
          },
          "column_min_values_range_estimator": {
            "metric_configuration": {
              "domain_kwargs": {
                "column": "e"
              },
              "metric_dependencies": null,
              "metric_name": "column.min",
              "metric_value_kwargs": null
            },
            "num_batches": 1
          }
        }
      }
    },
    {
      "expectation_type": "expect_column_quantile_values_to_be_between",
      "kwargs": {
        "allow_relative_error": false,
        "column": "e",
        "quantile_ranges": {
          "quantiles": [
            0.25,
            0.5,
            0.75
          ],
          "value_ranges": [
            [
              2,
              2
            ],
            [
              5,
              5
            ],
            [
              8,
              8
            ]
          ]
        }
      },
      "meta": {
        "profiler_details": {
          "metric_configuration": {
            "domain_kwargs": {
              "column": "e"
            },
            "metric_dependencies": null,
            "metric_name": "column.quantile_values",
            "metric_value_kwargs": {
              "allow_relative_error": false,
              "quantiles": [
                0.25,
                0.5,
                0.75
              ]
            }
          },
          "num_batches": 1
        }
      }
    },
    {
      "expectation_type": "expect_column_median_to_be_between",
      "kwargs": {
        "column": "e",
        "max_value": 5.0,
        "min_value": 5.0,
        "strict_max": false,
        "strict_min": false
      },
      "meta": {
        "profiler_details": {
          "metric_configuration": {
            "domain_kwargs": {
              "column": "e"
            },
            "metric_dependencies": null,
            "metric_name": "column.median",
            "metric_value_kwargs": null
          },
          "num_batches": 1
        }
      }
    },
    {
      "expectation_type": "expect_column_mean_to_be_between",
      "kwargs": {
        "column": "e",
        "max_value": 5.0,
        "min_value": 5.0,
        "strict_max": false,
        "strict_min": false
      },
      "meta": {
        "profiler_details": {
          "metric_configuration": {
            "domain_kwargs": {
              "column": "e"
            },
            "metric_dependencies": null,
            "metric_name": "column.mean",
            "metric_value_kwargs": null
          },
          "num_batches": 1
        }
      }
    },
    {
      "expectation_type": "expect_column_stdev_to_be_between",
      "kwargs": {
        "column": "e",
        "max_value": 3.0,
        "min_value": 3.0,
        "strict_max": false,
        "strict_min": false
      },
      "meta": {
        "profiler_details": {
          "metric_configuration": {
            "domain_kwargs": {
              "column": "e"
            },
            "metric_dependencies": null,
            "metric_name": "column.standard_deviation",
            "metric_value_kwargs": null
          },
          "num_batches": 1
        }
      }
    },
    {
      "expectation_type": "expect_column_min_to_be_between",
      "kwargs": {
        "column": "b",
        "max_value": 3,
        "min_value": 3,
        "strict_max": false,
        "strict_min": false
      },
      "meta": {
        "profiler_details": {
          "metric_configuration": {
            "domain_kwargs": {
              "column": "b"
            },
            "metric_dependencies": null,
            "metric_name": "column.min",
            "metric_value_kwargs": null
          },
          "num_batches": 1
        }
      }
    },
    {
      "expectation_type": "expect_column_max_to_be_between",
      "kwargs": {
        "column": "b",
        "max_value": 9,
        "min_value": 9,
        "strict_max": false,
        "strict_min": false
      },
      "meta": {
        "profiler_details": {
          "metric_configuration": {
            "domain_kwargs": {
              "column": "b"
            },
            "metric_dependencies": null,
            "metric_name": "column.max",
            "metric_value_kwargs": null
          },
          "num_batches": 1
        }
      }
    },
    {
      "expectation_type": "expect_column_values_to_be_between",
      "kwargs": {
        "column": "b",
        "max_value": 9,
        "min_value": 3,
        "mostly": 1.0,
        "strict_max": false,
        "strict_min": false
      },
      "meta": {
        "profiler_details": {
          "column_max_values_range_estimator": {
            "metric_configuration": {
              "domain_kwargs": {
                "column": "b"
              },
              "metric_dependencies": null,
              "metric_name": "column.max",
              "metric_value_kwargs": null
            },
            "num_batches": 1
          },
          "column_min_values_range_estimator": {
            "metric_configuration": {
              "domain_kwargs": {
                "column": "b"
              },
              "metric_dependencies": null,
              "metric_name": "column.min",
              "metric_value_kwargs": null
            },
            "num_batches": 1
          }
        }
      }
    },
    {
      "expectation_type": "expect_column_quantile_values_to_be_between",
      "kwargs": {
        "allow_relative_error": false,
        "column": "b",
        "quantile_ranges": {
          "quantiles": [
            0.25,
            0.5,
            0.75
          ],
          "value_ranges": [
            [
              3,
              3
            ],
            [
              6,
              6
            ],
            [
              9,
              9
            ]
          ]
        }
      },
      "meta": {
        "profiler_details": {
          "metric_configuration": {
            "domain_kwargs": {
              "column": "b"
            },
            "metric_dependencies": null,
            "metric_name": "column.quantile_values",
            "metric_value_kwargs": {
              "allow_relative_error": false,
              "quantiles": [
                0.25,
                0.5,
                0.75
              ]
            }
          },
          "num_batches": 1
        }
      }
    },
    {
      "expectation_type": "expect_column_median_to_be_between",
      "kwargs": {
        "column": "b",
        "max_value": 6.0,
        "min_value": 6.0,
        "strict_max": false,
        "strict_min": false
      },
      "meta": {
        "profiler_details": {
          "metric_configuration": {
            "domain_kwargs": {
              "column": "b"
            },
            "metric_dependencies": null,
            "metric_name": "column.median",
            "metric_value_kwargs": null
          },
          "num_batches": 1
        }
      }
    },
    {
      "expectation_type": "expect_column_mean_to_be_between",
      "kwargs": {
        "column": "b",
        "max_value": 6.0,
        "min_value": 6.0,
        "strict_max": false,
        "strict_min": false
      },
      "meta": {
        "profiler_details": {
          "metric_configuration": {
            "domain_kwargs": {
              "column": "b"
            },
            "metric_dependencies": null,
            "metric_name": "column.mean",
            "metric_value_kwargs": null
          },
          "num_batches": 1
        }
      }
    },
    {
      "expectation_type": "expect_column_stdev_to_be_between",
      "kwargs": {
        "column": "b",
        "max_value": 3.0,
        "min_value": 3.0,
        "strict_max": false,
        "strict_min": false
      },
      "meta": {
        "profiler_details": {
          "metric_configuration": {
            "domain_kwargs": {
              "column": "b"
            },
            "metric_dependencies": null,
            "metric_name": "column.standard_deviation",
            "metric_value_kwargs": null
          },
          "num_batches": 1
        }
      }
    },
    {
      "expectation_type": "expect_column_values_to_be_in_set",
      "kwargs": {
        "column": "a",
        "mostly": 1.0,
        "value_set": [
          1,
          4,
          7
        ]
      },
      "meta": {
        "profiler_details": {
          "metric_configuration": {
            "domain_kwargs": {
              "column": "a"
            },
            "metric_dependencies": null,
            "metric_name": "column.distinct_values",
            "metric_value_kwargs": null
          },
          "num_batches": 1
        }
      }
    },
    {
      "expectation_type": "expect_column_unique_value_count_to_be_between",
      "kwargs": {
        "column": "a",
        "max_value": 3,
        "min_value": 3,
        "strict_max": false,
        "strict_min": false
      },
      "meta": {
        "profiler_details": {
          "metric_configuration": {
            "domain_kwargs": {
              "column": "a"
            },
            "metric_dependencies": null,
            "metric_name": "column.distinct_values.count",
            "metric_value_kwargs": null
          },
          "num_batches": 1
        }
      }
    },
    {
      "expectation_type": "expect_column_proportion_of_unique_values_to_be_between",
      "kwargs": {
        "column": "a",
        "max_value": 1.0,
        "min_value": 1.0,
        "strict_max": false,
        "strict_min": false
      },
      "meta": {
        "profiler_details": {
          "metric_configuration": {
            "domain_kwargs": {
              "column": "a"
            },
            "metric_dependencies": null,
            "metric_name": "column.unique_proportion",
            "metric_value_kwargs": null
          },
          "num_batches": 1
        }
      }
    },
    {
      "expectation_type": "expect_column_values_to_be_in_set",
      "kwargs": {
        "column": "e",
        "mostly": 1.0,
        "value_set": [
          8,
          2,
          5
        ]
      },
      "meta": {
        "profiler_details": {
          "metric_configuration": {
            "domain_kwargs": {
              "column": "e"
            },
            "metric_dependencies": null,
            "metric_name": "column.distinct_values",
            "metric_value_kwargs": null
          },
          "num_batches": 1
        }
      }
    },
    {
      "expectation_type": "expect_column_unique_value_count_to_be_between",
      "kwargs": {
        "column": "e",
        "max_value": 3,
        "min_value": 3,
        "strict_max": false,
        "strict_min": false
      },
      "meta": {
        "profiler_details": {
          "metric_configuration": {
            "domain_kwargs": {
              "column": "e"
            },
            "metric_dependencies": null,
            "metric_name": "column.distinct_values.count",
            "metric_value_kwargs": null
          },
          "num_batches": 1
        }
      }
    },
    {
      "expectation_type": "expect_column_proportion_of_unique_values_to_be_between",
      "kwargs": {
        "column": "e",
        "max_value": 1.0,
        "min_value": 1.0,
        "strict_max": false,
        "strict_min": false
      },
      "meta": {
        "profiler_details": {
          "metric_configuration": {
            "domain_kwargs": {
              "column": "e"
            },
            "metric_dependencies": null,
            "metric_name": "column.unique_proportion",
            "metric_value_kwargs": null
          },
          "num_batches": 1
        }
      }
    },
    {
      "expectation_type": "expect_column_values_to_be_in_set",
      "kwargs": {
        "column": "b",
        "mostly": 1.0,
        "value_set": [
          9,
          3,
          6
        ]
      },
      "meta": {
        "profiler_details": {
          "metric_configuration": {
            "domain_kwargs": {
              "column": "b"
            },
            "metric_dependencies": null,
            "metric_name": "column.distinct_values",
            "metric_value_kwargs": null
          },
          "num_batches": 1
        }
      }
    },
    {
      "expectation_type": "expect_column_unique_value_count_to_be_between",
      "kwargs": {
        "column": "b",
        "max_value": 3,
        "min_value": 3,
        "strict_max": false,
        "strict_min": false
      },
      "meta": {
        "profiler_details": {
          "metric_configuration": {
            "domain_kwargs": {
              "column": "b"
            },
            "metric_dependencies": null,
            "metric_name": "column.distinct_values.count",
            "metric_value_kwargs": null
          },
          "num_batches": 1
        }
      }
    },
    {
      "expectation_type": "expect_column_proportion_of_unique_values_to_be_between",
      "kwargs": {
        "column": "b",
        "max_value": 1.0,
        "min_value": 1.0,
        "strict_max": false,
        "strict_min": false
      },
      "meta": {
        "profiler_details": {
          "metric_configuration": {
            "domain_kwargs": {
              "column": "b"
            },
            "metric_dependencies": null,
            "metric_name": "column.unique_proportion",
            "metric_value_kwargs": null
          },
          "num_batches": 1
        }
      }
    }
  ],
  "ge_cloud_id": null,
  "meta": {
    "citations": [
      {
        "citation_date": "2022-10-26T11:02:39.986273Z",
        "comment": "Created by effective Rule-Based Profiler of OnboardingDataAssistant with the configuration included.\n"
      }
    ],
    "great_expectations_version": "0.15.16"
  }
}